{"dependencies":[{"name":"babel-runtime/helpers/extends","loc":{"line":1,"column":21}},{"name":"classnames","loc":{"line":2,"column":15}},{"name":"prop-types","loc":{"line":3,"column":22}},{"name":"react","loc":{"line":4,"column":18}},{"name":"../../lib","loc":{"line":6,"column":112}}],"generated":{"js":"\"use strict\";Object.defineProperty(exports,\"__esModule\",{value:!0});var e=require(\"babel-runtime/helpers/extends\"),r=c(e),t=require(\"classnames\"),a=c(t),n=require(\"prop-types\"),l=c(n),s=require(\"react\"),d=c(s),u=require(\"../../lib\");function c(e){return e&&e.__esModule?e:{default:e}}function o(e){var t=e.children,n=e.className,l=e.content,s=(0,a.default)(n,\"header\"),c=(0,u.getUnhandledProps)(o,e),i=(0,u.getElementType)(o,e);return d.default.createElement(i,(0,r.default)({},c,{className:s}),u.childrenUtils.isNil(t)?l:t)}o.handledProps=[\"as\",\"children\",\"className\",\"content\"],o._meta={name:\"ModalHeader\",type:u.META.TYPES.MODULE,parent:\"Modal\"},o.propTypes={},o.create=(0,u.createShorthandFactory)(o,function(e){return{content:e}}),exports.default=o;"},"hash":"87451419626a476d294957e51f947ba9"}